fused_local_corr.libs/libgomp-e985bcbb.so.1.0.0
local_corr/_C.cpython-310-x86_64-linux-gnu.so
local_corr/__init__.py
local_corr/ops.py
local_corr/csrc/corr.cpp
local_corr/csrc/cuda/corr.cu
fused_local_corr-0.2.3.dist-info/METADATA
fused_local_corr-0.2.3.dist-info/WHEEL
fused_local_corr-0.2.3.dist-info/top_level.txt
fused_local_corr-0.2.3.dist-info/RECORD
fused_local_corr-0.2.3.dist-info/licenses/LICENSE
