Metadata-Version: 2.4
Name: fused-local-corr
Version: 0.2.3
Summary: Fused Local Correlation in PyTorch
Author-email: Johan Edstedt <johan.edstedt@liu.se>
License: MIT License
Requires-Python: >=3.9
License-File: LICENSE
Requires-Dist: torch
Requires-Dist: numpy
Dynamic: license-file
